skoots/__init__.py
skoots/__main__.py
skoots/config.py
skoots/lib/__init__.py
skoots/lib/cropper.py
skoots/lib/custom_types.py
skoots/lib/embedding_to_prob.py
skoots/lib/eval.py
skoots/lib/eval_test.py
skoots/lib/flood_fill.py
skoots/lib/merge.py
skoots/lib/morphology.py
skoots/lib/mp_utils.py
skoots/lib/skeleton.py
skoots/lib/types.py
skoots/lib/utils.py
skoots/lib/vector_to_embedding.py
skoots/tests/__init__.py
skoots/tests/skel.py
skoots/train/__init__.py
skoots/train/__main__.py
skoots/train/dataloader.py
skoots/train/engine.py
skoots/train/erosion.py
skoots/train/generate_skeletons.py
skoots/train/loss.py
skoots/train/merged_transform.py
skoots/train/setup.py
skoots/train/sigma.py
skoots/train/test_engine.py
skoots/train/utils.py
skoots/utils/__init__.py
skoots/utils/convert_trch_to_tif.py
skoots/validate/__init__.py
skoots/validate/__main__.py
skoots/validate/compare.py
skoots/validate/lib.py
skoots/validate/stats.py
skoots/validate/utils.py
skoots-0.0.5.dist-info/LICENSE
skoots-0.0.5.dist-info/METADATA
skoots-0.0.5.dist-info/WHEEL
skoots-0.0.5.dist-info/entry_points.txt
skoots-0.0.5.dist-info/top_level.txt
skoots-0.0.5.dist-info/RECORD
